aybrequests/__init__.py
aybrequests/request.py
aybrequests/session.py
aybrequests/url_utils.py
AYBRequests-0.4.1.dist-info/METADATA
AYBRequests-0.4.1.dist-info/WHEEL
AYBRequests-0.4.1.dist-info/top_level.txt
AYBRequests-0.4.1.dist-info/RECORD
